hexedhash/__init__.py
hexedhash/hasher.py
hexedhash/hashgen.py
hexedhash/main.py
package/__init__.py
package/main.py
hexedhash-1.0.0.dist-info/LICENSE
hexedhash-1.0.0.dist-info/METADATA
hexedhash-1.0.0.dist-info/WHEEL
hexedhash-1.0.0.dist-info/top_level.txt
hexedhash-1.0.0.dist-info/RECORD
