Metadata-Version: 2.1
Name: hexedhash
Version: 1.0.0
Summary: Creates hash by salt + hex
Home-page: https://github.com/ltcp-security
Author: maj0r
Classifier: Programming Language :: Python :: 3.11
Classifier: License :: OSI Approved :: MIT License
Classifier: Operating System :: OS Independent
Requires-Python: >=3.10
License-File: LICENSE
